{
    "swagger": "2.0",
    "info": {
        "description": "This is an API of payment-service for Socialweb application",
        "title": "Local-Template-Entity Swagger",
        "contact": {},
        "version": "1.0"
    },
    "basePath": "/api/v1",
    "paths": {
        "/entity/create": {
            "post": {
                "security": [
                    {
                        "ApiKeyAuth": []
                    }
                ],
                "description": "Test endpoint crud",
                "consumes": [
                    "application/json"
                ],
                "produces": [
                    "application/json"
                ],
                "tags": [
                    "Entity"
                ],
                "summary": "CreateEntity info",
                "parameters": [
                    {
                        "description": "Entity data",
                        "name": "company",
                        "in": "body",
                        "required": true,
                        "schema": {
                            "$ref": "#/definitions/types.EntityRequest"
                        }
                    }
                ],
                "responses": {
                    "200": {
                        "description": "OK",
                        "schema": {
                            "type": "array",
                            "items": {
                                "$ref": "#/definitions/types.SuccessResponseData"
                            }
                        }
                    },
                    "400": {
                        "description": "Bad Request",
                        "schema": {
                            "$ref": "#/definitions/types.FailureResponse"
                        }
                    },
                    "500": {
                        "description": "Internal Server Error",
                        "schema": {
                            "$ref": "#/definitions/types.FailureErrorResponse"
                        }
                    }
                }
            }
        },
        "/entity/delete/{id}": {
            "delete": {
                "security": [
                    {
                        "ApiKeyAuth": []
                    }
                ],
                "description": "Test endpoint crud",
                "consumes": [
                    "application/json"
                ],
                "produces": [
                    "application/json"
                ],
                "tags": [
                    "Entity"
                ],
                "summary": "DeleteEntity info",
                "parameters": [
                    {
                        "type": "string",
                        "description": "Entity ID",
                        "name": "id",
                        "in": "path",
                        "required": true
                    }
                ],
                "responses": {
                    "200": {
                        "description": "OK",
                        "schema": {
                            "type": "array",
                            "items": {
                                "$ref": "#/definitions/types.SuccessResponseData"
                            }
                        }
                    },
                    "400": {
                        "description": "Bad Request",
                        "schema": {
                            "$ref": "#/definitions/types.FailureResponse"
                        }
                    },
                    "500": {
                        "description": "Internal Server Error",
                        "schema": {
                            "$ref": "#/definitions/types.FailureErrorResponse"
                        }
                    }
                }
            }
        },
        "/entity/get": {
            "get": {
                "security": [
                    {
                        "ApiKeyAuth": []
                    }
                ],
                "description": "Test endpoint crud",
                "consumes": [
                    "application/json"
                ],
                "produces": [
                    "application/json"
                ],
                "tags": [
                    "Entity"
                ],
                "summary": "GetEntity info",
                "responses": {
                    "200": {
                        "description": "OK",
                        "schema": {
                            "type": "array",
                            "items": {
                                "$ref": "#/definitions/types.SuccessResponseData"
                            }
                        }
                    },
                    "400": {
                        "description": "Bad Request",
                        "schema": {
                            "$ref": "#/definitions/types.FailureResponse"
                        }
                    },
                    "500": {
                        "description": "Internal Server Error",
                        "schema": {
                            "$ref": "#/definitions/types.FailureErrorResponse"
                        }
                    }
                }
            }
        },
        "/entity/test-grpc": {
            "get": {
                "security": [
                    {
                        "ApiKeyAuth": []
                    }
                ],
                "description": "Test endpoint for gRPC communication with auth service",
                "consumes": [
                    "application/json"
                ],
                "produces": [
                    "application/json"
                ],
                "tags": [
                    "grpc"
                ],
                "summary": "Test gRPC connection to auth service",
                "responses": {
                    "200": {
                        "description": "OK",
                        "schema": {
                            "$ref": "#/definitions/types.SuccessResponseData"
                        }
                    },
                    "400": {
                        "description": "Bad Request",
                        "schema": {
                            "$ref": "#/definitions/types.FailureResponse"
                        }
                    },
                    "500": {
                        "description": "Internal Server Error",
                        "schema": {
                            "$ref": "#/definitions/types.FailureErrorResponse"
                        }
                    }
                }
            }
        },
        "/entity/test-grpc-user-info": {
            "get": {
                "security": [
                    {
                        "ApiKeyAuth": []
                    }
                ],
                "description": "Test endpoint for gRPC communication with auth service",
                "consumes": [
                    "application/json"
                ],
                "produces": [
                    "application/json"
                ],
                "tags": [
                    "grpc"
                ],
                "summary": "Test gRPC connection to auth service",
                "responses": {
                    "200": {
                        "description": "OK",
                        "schema": {
                            "$ref": "#/definitions/types.SuccessResponseData"
                        }
                    },
                    "400": {
                        "description": "Bad Request",
                        "schema": {
                            "$ref": "#/definitions/types.FailureResponse"
                        }
                    },
                    "500": {
                        "description": "Internal Server Error",
                        "schema": {
                            "$ref": "#/definitions/types.FailureErrorResponse"
                        }
                    }
                }
            }
        },
        "/entity/update/{id}": {
            "patch": {
                "security": [
                    {
                        "ApiKeyAuth": []
                    }
                ],
                "description": "Test endpoint crud",
                "consumes": [
                    "application/json"
                ],
                "produces": [
                    "application/json"
                ],
                "tags": [
                    "Entity"
                ],
                "summary": "UpdateEntity info",
                "parameters": [
                    {
                        "type": "string",
                        "description": "Entity ID",
                        "name": "id",
                        "in": "path",
                        "required": true
                    },
                    {
                        "description": "Entity data",
                        "name": "company",
                        "in": "body",
                        "required": true,
                        "schema": {
                            "$ref": "#/definitions/types.EntityRequest"
                        }
                    }
                ],
                "responses": {
                    "200": {
                        "description": "OK",
                        "schema": {
                            "type": "array",
                            "items": {
                                "$ref": "#/definitions/types.SuccessResponseData"
                            }
                        }
                    },
                    "400": {
                        "description": "Bad Request",
                        "schema": {
                            "$ref": "#/definitions/types.FailureResponse"
                        }
                    },
                    "500": {
                        "description": "Internal Server Error",
                        "schema": {
                            "$ref": "#/definitions/types.FailureErrorResponse"
                        }
                    }
                }
            }
        }
    },
    "definitions": {
        "types.EntityRequest": {
            "type": "object",
            "properties": {
                "description": {
                    "type": "string"
                }
            }
        },
        "types.FailureErrorResponse": {
            "type": "object",
            "properties": {
                "error": {
                    "type": "string"
                },
                "message": {
                    "type": "string"
                },
                "status": {
                    "type": "string"
                }
            }
        },
        "types.FailureResponse": {
            "type": "object",
            "properties": {
                "message": {
                    "type": "string"
                },
                "status": {
                    "type": "string"
                }
            }
        },
        "types.SuccessResponseData": {
            "type": "object",
            "properties": {
                "data": {},
                "message": {
                    "type": "string"
                },
                "status": {
                    "type": "string"
                }
            }
        }
    },
    "securityDefinitions": {
        "ApiKeyAuth": {
            "description": "Description for what is this security definition being used",
            "type": "apiKey",
            "name": "Authorization",
            "in": "header"
        }
    }
}